hate_speech_detector/__init__.py
hate_speech_detector/model.py
hate_speech_detector/preprocessing.py
hate_speech_detector-0.2.1.dist-info/licenses/LICENSE
hate_speech_detector-0.2.1.dist-info/METADATA
hate_speech_detector-0.2.1.dist-info/WHEEL
hate_speech_detector-0.2.1.dist-info/top_level.txt
hate_speech_detector-0.2.1.dist-info/RECORD
