Metadata-Version: 2.4
Name: hate_speech_detector
Version: 0.2.1
Summary: A simple hate speech detection model using machine learning.
Author: Jahfar Muhammed
Author-email: jahfarbinmuhammed117@gmail.com
License: MIT
Classifier: Programming Language :: Python :: 3
Classifier: License :: OSI Approved :: MIT License
Classifier: Operating System :: OS Independent
Requires-Python: >=3.7
License-File: LICENSE
Requires-Dist: nltk
Requires-Dist: regex
Requires-Dist: joblib
Dynamic: author
Dynamic: author-email
Dynamic: classifier
Dynamic: description
Dynamic: description-content-type
Dynamic: license
Dynamic: license-file
Dynamic: requires-dist
Dynamic: requires-python
Dynamic: summary
